understory/apps/micropub_server/__init__.py
understory/apps/micropub_server/content/__init__.py
understory/apps/micropub_server/content/templates/__init__.py
understory/apps/micropub_server/content/templates/entry.html
understory/apps/micropub_server/content/templates/homepage.html
understory/apps/micropub_server/content/templates/post_not_found.html
understory/apps/micropub_server/media/__init__.py
understory/apps/micropub_server/media/templates/__init__.py
understory/apps/micropub_server/media/templates/media.html
understory/apps/micropub_server/posts/__init__.py
understory/apps/micropub_server/posts/templates/__init__.py
understory/apps/micropub_server/posts/templates/activity.html
understory/apps/micropub_server/posts/templates/card.html
understory/apps/micropub_server/posts/templates/cards.html
understory/apps/micropub_server/posts/templates/channel.html
understory/apps/micropub_server/posts/templates/channels.html
understory/apps/micropub_server/posts/templates/entries.html
understory/apps/micropub_server/posts/templates/render_dict.html
understory/apps/micropub_server/posts/templates/rooms.html
understory/apps/micropub_server/posts/templates/syndication.html
understory_micropub_server-0.0.7.dist-info/entry_points.txt
understory_micropub_server-0.0.7.dist-info/LICENSE
understory_micropub_server-0.0.7.dist-info/WHEEL
understory_micropub_server-0.0.7.dist-info/METADATA
understory_micropub_server-0.0.7.dist-info/RECORD
